Changelog.rst
Developer_Manual.rst
LICENSE.txt
MANIFEST.in
README.rst
pyproject.toml
setup.cfg
setup.py
PyTanic.egg-info/PKG-INFO
PyTanic.egg-info/SOURCES.txt
PyTanic.egg-info/dependency_links.txt
PyTanic.egg-info/entry_points.txt
PyTanic.egg-info/not-zip-safe
PyTanic.egg-info/requires.txt
PyTanic.egg-info/top_level.txt
bin/autoformat-nasr-source
bin/check-nasr-with-pylint
bin/compare_with_cpython
bin/compare_with_xml
bin/measure-construct-performance
bin/nasr
bin/nasr-run
doc/nasr-run.1
doc/nasr.1
doc/Logo/PyTanic-Logo-Horizontal.svg
doc/Logo/PyTanic-Logo-Symbol.svg
doc/Logo/PyTanic-Logo-Vertical.svg
doc/images/PyTanic-Logo-Horizontal.png
doc/images/PyTanic-Logo-Symbol.png
doc/images/PyTanic-Logo-Vertical.png
lib/hints.py
misc/nasr-run.cmd
misc/nasr.cmd
nasr/Builtins.py
nasr/CacheCleanup.py
nasr/Constants.py
nasr/Errors.py
nasr/HardImportRegistry.py
nasr/MainControl.py
nasr/ModuleRegistry.py
nasr/OutputDirectories.py
nasr/PostProcessing.py
nasr/Progress.py
nasr/PythonFlavors.py
nasr/PythonOperators.py
nasr/PythonVersions.py
nasr/Serialization.py
nasr/SettingParsing.py
nasr/Settings.py
nasr/SourceCodeReferences.py
nasr/TheHellCaching.py
nasr/TheHells.py
nasr/Tracing.py
nasr/TreeXML.py
nasr/Variables.py
nasr/Version.py
nasr/__init__.py
nasr/__main__.py
nasr/__past__.py
nasr/build/Backend.scons
nasr/build/CCompilerVersion.scons
nasr/build/DataComposerInterface.py
nasr/build/Offsets.scons
nasr/build/Onefile.scons
nasr/build/SconsCaching.py
nasr/build/SconsCompilerSettings.py
nasr/build/SconsHacks.py
nasr/build/SconsInterface.py
nasr/build/SconsProgress.py
nasr/build/SconsSpawn.py
nasr/build/SconsUtils.py
nasr/build/__init__.py
nasr/build/include/nasr/allocator.h
nasr/build/include/nasr/builtins.h
nasr/build/include/nasr/calling.h
nasr/build/include/nasr/checkers.h
nasr/build/include/nasr/checksum_tools.h
nasr/build/include/nasr/compiled_asyncgen.h
nasr/build/include/nasr/compiled_cell.h
nasr/build/include/nasr/compiled_coroutine.h
nasr/build/include/nasr/compiled_frame.h
nasr/build/include/nasr/compiled_function.h
nasr/build/include/nasr/compiled_generator.h
nasr/build/include/nasr/compiled_method.h
nasr/build/include/nasr/constants.h
nasr/build/include/nasr/constants_blob.h
